emacs_daemon_tray_icon-0.0.1.dist-info/DESCRIPTION.rst
emacs_daemon_tray_icon-0.0.1.dist-info/METADATA
emacs_daemon_tray_icon-0.0.1.dist-info/RECORD
emacs_daemon_tray_icon-0.0.1.dist-info/WHEEL
emacs_daemon_tray_icon-0.0.1.dist-info/entry_points.txt
emacs_daemon_tray_icon-0.0.1.dist-info/metadata.json
emacs_daemon_tray_icon-0.0.1.dist-info/top_level.txt
src/__init__.py
