Metadata-Version: 2.0
Name: emacs-daemon-tray-icon
Version: 0.0.1
Summary: Emacs daemon systray icon
Home-page: UNKNOWN
Author: Michał Chałupczak
Author-email: michal@chalupczak.info
License: BSD
Keywords: emacs editor tool
Platform: UNKNOWN
Classifier: Development Status :: 3 - Alpha
Classifier: Topic :: Utilities
Classifier: License :: OSI Approved :: BSD License
Requires-Dist: Pillow
Requires-Dist: psutil
Requires-Dist: pystray
